{
  "version": "6",
  "dialect": "sqlite",
  "id": "c917fb75-8fe6-4bba-b616-5a7041e4e9d6",
  "prevId": "8422a8dd-14bf-4577-9af2-98c3fba8b59f",
  "tables": {
    "mcp_rate_limit_buckets": {
      "name": "mcp_rate_limit_buckets",
      "columns": {
        "client_key": {
          "name": "client_key",
          "type": "text",
          "primaryKey": true,
          "notNull": true,
          "autoincrement": false
        },
        "window_started_at": {
          "name": "window_started_at",
          "type": "integer",
          "primaryKey": false,
          "notNull": true,
          "autoincrement": false
        },
        "count": {
          "name": "count",
          "type": "integer",
          "primaryKey": false,
          "notNull": true,
          "autoincrement": false
        },
        "updated_at": {
          "name": "updated_at",
          "type": "text",
          "primaryKey": false,
          "notNull": true,
          "autoincrement": false,
          "default": "CURRENT_TIMESTAMP"
        }
      },
      "indexes": {
        "mcp_rate_limit_buckets_window_idx": {
          "name": "mcp_rate_limit_buckets_window_idx",
          "columns": [
            "window_started_at"
          ],
          "isUnique": false
        }
      },
      "foreignKeys": {},
      "compositePrimaryKeys": {},
      "uniqueConstraints": {},
      "checkConstraints": {}
    },
    "source_intake_records": {
      "name": "source_intake_records",
      "columns": {
        "id": {
          "name": "id",
          "type": "text",
          "primaryKey": true,
          "notNull": true,
          "autoincrement": false
        },
        "case_id": {
          "name": "case_id",
          "type": "text",
          "primaryKey": false,
          "notNull": true,
          "autoincrement": false
        },
        "case_title": {
          "name": "case_title",
          "type": "text",
          "primaryKey": false,
          "notNull": true,
          "autoincrement": false
        },
        "status": {
          "name": "status",
          "type": "text",
          "primaryKey": false,
          "notNull": true,
          "autoincrement": false
        },
        "source_count": {
          "name": "source_count",
          "type": "integer",
          "primaryKey": false,
          "notNull": true,
          "autoincrement": false
        },
        "reachable_count": {
          "name": "reachable_count",
          "type": "integer",
          "primaryKey": false,
          "notNull": true,
          "autoincrement": false
        },
        "failed_count": {
          "name": "failed_count",
          "type": "integer",
          "primaryKey": false,
          "notNull": true,
          "autoincrement": false
        },
        "generated_at": {
          "name": "generated_at",
          "type": "text",
          "primaryKey": false,
          "notNull": true,
          "autoincrement": false
        },
        "report_json": {
          "name": "report_json",
          "type": "text",
          "primaryKey": false,
          "notNull": true,
          "autoincrement": false
        },
        "created_at": {
          "name": "created_at",
          "type": "text",
          "primaryKey": false,
          "notNull": true,
          "autoincrement": false,
          "default": "CURRENT_TIMESTAMP"
        },
        "updated_at": {
          "name": "updated_at",
          "type": "text",
          "primaryKey": false,
          "notNull": true,
          "autoincrement": false,
          "default": "CURRENT_TIMESTAMP"
        }
      },
      "indexes": {
        "source_intake_records_case_idx": {
          "name": "source_intake_records_case_idx",
          "columns": [
            "case_id"
          ],
          "isUnique": false
        },
        "source_intake_records_status_idx": {
          "name": "source_intake_records_status_idx",
          "columns": [
            "status"
          ],
          "isUnique": false
        },
        "source_intake_records_created_idx": {
          "name": "source_intake_records_created_idx",
          "columns": [
            "created_at"
          ],
          "isUnique": false
        }
      },
      "foreignKeys": {},
      "compositePrimaryKeys": {},
      "uniqueConstraints": {},
      "checkConstraints": {}
    },
    "source_intake_review_events": {
      "name": "source_intake_review_events",
      "columns": {
        "id": {
          "name": "id",
          "type": "text",
          "primaryKey": true,
          "notNull": true,
          "autoincrement": false
        },
        "record_id": {
          "name": "record_id",
          "type": "text",
          "primaryKey": false,
          "notNull": true,
          "autoincrement": false
        },
        "from_status": {
          "name": "from_status",
          "type": "text",
          "primaryKey": false,
          "notNull": false,
          "autoincrement": false
        },
        "to_status": {
          "name": "to_status",
          "type": "text",
          "primaryKey": false,
          "notNull": true,
          "autoincrement": false
        },
        "note": {
          "name": "note",
          "type": "text",
          "primaryKey": false,
          "notNull": true,
          "autoincrement": false,
          "default": "''"
        },
        "actor": {
          "name": "actor",
          "type": "text",
          "primaryKey": false,
          "notNull": true,
          "autoincrement": false,
          "default": "'api'"
        },
        "created_at": {
          "name": "created_at",
          "type": "text",
          "primaryKey": false,
          "notNull": true,
          "autoincrement": false,
          "default": "CURRENT_TIMESTAMP"
        }
      },
      "indexes": {
        "source_intake_review_events_record_idx": {
          "name": "source_intake_review_events_record_idx",
          "columns": [
            "record_id"
          ],
          "isUnique": false
        },
        "source_intake_review_events_created_idx": {
          "name": "source_intake_review_events_created_idx",
          "columns": [
            "created_at"
          ],
          "isUnique": false
        }
      },
      "foreignKeys": {},
      "compositePrimaryKeys": {},
      "uniqueConstraints": {},
      "checkConstraints": {}
    }
  },
  "views": {},
  "enums": {},
  "_meta": {
    "schemas": {},
    "tables": {},
    "columns": {}
  },
  "internal": {
    "indexes": {}
  }
}